{"National":{"before":"282","after":"274","percent":"-2.84"},"Alabama":{"before":"269","after":"264","percent":"-1.86"},"Alaska":{"before":"274","after":"270","percent":"-1.46"},"Arizona":{"before":"280","after":"271","percent":"-3.21"},"Arkansas":{"before":"274","after":"267","percent":"-2.55"},"California":{"before":"276","after":"270","percent":"-2.17"},"Colorado":{"before":"285","after":"275","percent":"-3.51"},"Connecticut":{"before":"286","after":"276","percent":"-3.50"},"Delaware":{"before":"277","after":"264","percent":"-4.69"},"District of Columbia":{"before":"269","after":"260","percent":"-3.35"},"Florida":{"before":"279","after":"271","percent":"-2.87"},"Georgia":{"before":"279","after":"271","percent":"-2.87"},"Hawaii":{"before":"275","after":"270","percent":"-1.82"},"Idaho":{"before":"286","after":"282","percent":"-1.40"},"Illinois":{"before":"283","after":"275","percent":"-2.83"},"Indiana":{"before":"286","after":"279","percent":"-2.45"},"Iowa":{"before":"282","after":"277","percent":"-1.77"},"Kansas":{"before":"282","after":"272","percent":"-3.55"},"Kentucky":{"before":"278","after":"269","percent":"-3.24"},"Louisiana":{"before":"272","after":"266","percent":"-2.21"},"Maine":{"before":"282","after":"273","percent":"-3.19"},"Maryland":{"before":"280","after":"269","percent":"-3.93"},"Massachusetts":{"before":"294","after":"284","percent":"-3.40"},"Michigan":{"before":"280","after":"273","percent":"-2.50"},"Minnesota":{"before":"291","after":"280","percent":"-3.78"},"Mississippi":{"before":"274","after":"266","percent":"-2.92"},"Missouri":{"before":"281","after":"272","percent":"-3.20"},"Montana":{"before":"284","after":"277","percent":"-2.46"},"Nebraska":{"before":"285","after":"279","percent":"-2.11"},"Nevada":{"before":"274","after":"269","percent":"-1.82"},"New Hampshire":{"before":"287","after":"279","percent":"-2.79"},"New Jersey":{"before":"292","after":"281","percent":"-3.77"},"New Mexico":{"before":"269","after":"259","percent":"-3.72"},"New York":{"before":"280","after":"274","percent":"-2.14"},"North Carolina":{"before":"284","after":"274","percent":"-3.52"},"North Dakota":{"before":"286","after":"278","percent":"-2.80"},"Ohio":{"before":"286","after":"276","percent":"-3.50"},"Oklahoma":{"before":"276","after":"264","percent":"-4.35"},"Oregon":{"before":"280","after":"270","percent":"-3.57"},"Pennsylvania":{"before":"285","after":"274","percent":"-3.86"},"Puerto Rico":{"before":"222","after":"216","percent":"-2.70"},"Rhode Island":{"before":"276","after":"270","percent":"-2.17"},"South Carolina":{"before":"276","after":"269","percent":"-2.54"},"South Dakota":{"before":"287","after":"281","percent":"-2.09"},"Tennessee":{"before":"280","after":"272","percent":"-2.86"},"Texas":{"before":"280","after":"273","percent":"-2.50"},"Utah":{"before":"285","after":"282","percent":"-1.05"},"Vermont":{"before":"287","after":"276","percent":"-3.83"},"Virginia":{"before":"287","after":"279","percent":"-2.79"},"Washington":{"before":"286","after":"276","percent":"-3.50"},"West Virginia":{"before":"272","after":"260","percent":"-4.41"},"Wisconsin":{"before":"289","after":"281","percent":"-2.77"},"Wyoming":{"before":"286","after":"281","percent":"-1.75"},"undefined":{"percent":"NaN"}}